Flask_Perf-0.1.6.dist-info/METADATA
Flask_Perf-0.1.6.dist-info/RECORD
Flask_Perf-0.1.6.dist-info/WHEEL
Flask_Perf-0.1.6.dist-info/top_level.txt
flask_perf/__init__.py
