Metadata-Version: 2.1
Name: Flask-Perf
Version: 0.1.6
Summary: A simple profiler for flask applications.
Home-page: https://github.com/abetlen/Flask-Perf
Author: Andrei Betlen
Author-email: abetlen@gmail.com
License: MIT
Platform: any
Classifier: Environment :: Web Environment
Classifier: Intended Audience :: Developers
Classifier: License :: OSI Approved :: BSD License
Classifier: Operating System :: OS Independent
Classifier: Programming Language :: Python
Classifier: Topic :: Internet :: WWW/HTTP :: Dynamic Content
Classifier: Topic :: Software Development :: Libraries :: Python Modules
Provides-Extra: flask_sqlalchemy
Requires-Dist: Flask
Provides-Extra: flask_sqlalchemy
Requires-Dist: flask-sqlalchemy; extra == 'flask_sqlalchemy'
